geniusrise_listeners/__init__.py
geniusrise_listeners/activemq.py
geniusrise_listeners/amqp.py
geniusrise_listeners/grpc.py
geniusrise_listeners/http_polling.py
geniusrise_listeners/kafka.py
geniusrise_listeners/kinesis.py
geniusrise_listeners/mqtt.py
geniusrise_listeners/quic.py
geniusrise_listeners/redis_pubsub.py
geniusrise_listeners/redis_streams.py
geniusrise_listeners/sns.py
geniusrise_listeners/socketio.py
geniusrise_listeners/sqs.py
geniusrise_listeners/udp.py
geniusrise_listeners/webhook.py
geniusrise_listeners/websocket.py
geniusrise_listeners/zeromq.py
geniusrise_listeners-0.1.7.dist-info/METADATA
geniusrise_listeners-0.1.7.dist-info/WHEEL
geniusrise_listeners-0.1.7.dist-info/top_level.txt
geniusrise_listeners-0.1.7.dist-info/RECORD
